pycolorpy/__init__.py
pycolorpy/pycolorpy.py
pycolorpy-0.1.2.dist-info/LICENSE
pycolorpy-0.1.2.dist-info/WHEEL
pycolorpy-0.1.2.dist-info/METADATA
pycolorpy-0.1.2.dist-info/RECORD
